{"procedures":[{"id":";VsOjm.$$xbPo8AJo@iO","name":"TextTooLog","returnTypes":null,"parameters":[{"id":"HF]qPc%i_?ZT:dR`‾pPA","name":"info"}]},{"id":"YK43%W8NJf%p%mIa34v@","name":"OpenBrowser","returnTypes":[],"parameters":[{"id":"`[%Wl^[?@7}e=%wXN69?","name":"url"}]},{"id":"zR{j7UXY8G0.aFG+-9|B","name":"ReadData","returnTypes":[],"parameters":[{"id":"(ZrR.G)U‾D6p:mfi,74Y","name":"file_path"}]},{"id":"+j!jGVN3Mv0E/Czo,G37","name":"FillIncidentForm","returnTypes":null,"parameters":[{"id":"tNje|=NW)3a+Un8dqGPi","name":"input_data"},{"id":"k|xv$3T5o::kHMCVy[4#","name":"web_actions"}]},{"id":"5At`zE{nr$ASah*P.1Q#","name":"SubmitApplication","returnTypes":null,"parameters":[{"id":"4[`-Ag:2ZT2=etg5eN0j","name":"title"},{"id":"NI;^SwI/-=7d.Q|R{9c(","name":"reporter"},{"id":"d)Fcah(-@?yTxMQ$m8Og","name":"system"},{"id":":YHpIv5_|sjIDuAH8O$8","name":"severity"},{"id":"kk7y3-jj|%ps?Ye-.hwk","name":"web_actions"}]},{"id":"p49WwJAYkye^/!rH‾^Wr","name":"CheckTable","returnTypes":null,"parameters":[{"id":"yCn(G}tL$hiUjLV7;oP@","name":"input_data"},{"id":"5Z^!‾C‾Nb2X$RF@JPJ}H","name":"web_actions"}]}]}
